fluent_linter/__init__.py
fluent_linter/linter.py
moz_fluent_linter-0.4.9.dist-info/licenses/LICENSE
moz_fluent_linter-0.4.9.dist-info/METADATA
moz_fluent_linter-0.4.9.dist-info/WHEEL
moz_fluent_linter-0.4.9.dist-info/entry_points.txt
moz_fluent_linter-0.4.9.dist-info/top_level.txt
moz_fluent_linter-0.4.9.dist-info/RECORD
