Metadata-Version: 2.4
Name: moz-fluent-linter
Version: 0.4.9
Summary: Linter package used to check Fluent files
Home-page: https://github.com/mozilla-l10n/moz-fluent-linter
Author: Francesco Lodolo
Author-email: flod@mozilla.com
Project-URL: Bug Tracker, https://github.com/mozilla-l10n/moz-fluent-linter/issues
Classifier: Intended Audience :: Developers
Classifier: License :: OSI Approved :: Mozilla Public License 2.0 (MPL 2.0)
Classifier: Operating System :: OS Independent
Classifier: Programming Language :: Python :: 3
Classifier: Topic :: Software Development :: Libraries :: Python Modules
Classifier: Topic :: Software Development :: Localization
Requires-Python: >=3.7
License-File: LICENSE
Requires-Dist: fluent.syntax~=0.19.0
Requires-Dist: pyyaml
Requires-Dist: six
Dynamic: license-file
